_lef_parser_antlr/lefLexer.py
_lef_parser_antlr/lefListener.py
_lef_parser_antlr/lefParser.py
lef_parser/__init__.py
lef_parser/__version__.py
lef_parser/data.py
lef_parser/parse.py
lef_parser/py.typed
lef_parser-0.1.0.dist-info/METADATA
lef_parser-0.1.0.dist-info/WHEEL
lef_parser-0.1.0.dist-info/top_level.txt
lef_parser-0.1.0.dist-info/RECORD
