Metadata-Version: 2.1
Name: lef-parser
Version: 0.1.0
Summary: Antlr4-based parser for LEF files
Home-page: UNKNOWN
Author: Efabless Corporation and Contributors
Author-email: donn@efabless.com
License: UNKNOWN
Platform: UNKNOWN
Classifier: License :: OSI Approved :: Apache Software License
Classifier: Programming Language :: Python :: 3
Classifier: Intended Audience :: Developers
Classifier: Operating System :: POSIX :: Linux
Classifier: Operating System :: MacOS :: MacOS X
Requires-Python: >3.8
Requires-Dist: antlr4-python3-runtime ~=4.10.0
